redbean/__init__.py
redbean/config.py
redbean/dev_tools.py
redbean/exception.py
redbean/logging.py
redbean/logs.py
redbean/main.py
redbean/utils.py
redbean/web/__init__.py
redbean/web/application.py
redbean/web/resources.py
redbean/web/rest.py
redbean/web/session.py
redbean-0.6.5.dist-info/LICENSE
redbean-0.6.5.dist-info/METADATA
redbean-0.6.5.dist-info/WHEEL
redbean-0.6.5.dist-info/top_level.txt
redbean-0.6.5.dist-info/RECORD
