Metadata-Version: 2.1
Name: redbean
Version: 0.6.5
Summary: A tiny web framwork
Home-page: https://github.com/lcgong/redbean
Author: Chenggong Lyu
Author-email: lcgong@gmail.com
License: BSD
Platform: UNKNOWN
Classifier: Development Status :: 2 - Pre-Alpha
Classifier: Intended Audience :: Developers
Classifier: License :: OSI Approved :: BSD License
Classifier: Operating System :: Unix
Classifier: Operating System :: POSIX
Classifier: Operating System :: Microsoft :: Windows
Classifier: Programming Language :: Python
Classifier: Programming Language :: Python :: 3
Classifier: Programming Language :: Python :: 3.8
Classifier: Programming Language :: Python :: 3.9
Classifier: Programming Language :: Python :: Implementation :: CPython
Classifier: Topic :: Utilities
Requires-Dist: aiohttp (>=3.7)
Requires-Dist: toml (>=0.10)
Requires-Dist: cryptography (>=3.3)
Requires-Dist: watchgod (>=0.6)
Requires-Dist: pytest
